{
  "total_images": 1839,
  "last_updated": "2025-08-23T02:15:52.146Z",
  "counts": {
    "value_8": 78,
    "value_11": 96,
    "value_14": 87,
    "value_13": 92,
    "value_1": 118,
    "value_16": 58,
    "value_9": 61,
    "value_6": 68,
    "value_17": 81,
    "value_2": 108,
    "value_15": 106,
    "unclear": 106,
    "value_5": 79,
    "value_7": 69,
    "value_12": 90,
    "value_19": 76,
    "value_20": 136,
    "value_10": 97,
    "value_3": 90,
    "value_4": 73,
    "value_18": 70
  }
}